[
  {
    "id": 1,
    "name": "raelynn",
    "managerId": null
  },
  {
    "id": 2,
    "name": "darin",
    "managerId": 1
  },
  {
    "id": 3,
    "name": "kacie",
    "managerId": 1
  },
  {
    "id": 4,
    "name": "kacie",
    "managerId": 1
  },
  {
    "id": 5,
    "name": "kacie",
    "managerId": 2
  },
  {
    "id": 6,
    "name": "kacie",
    "managerId": 2
  },
  {
    "id": 7,
    "name": "kacie",
    "managerId": 2
  },
  {
    "id": 8,
    "name": "kacie",
    "managerId": 3
  },
  {
    "id": 9,
    "name": "kacie",
    "managerId": 3
  },
  {
    "id": 10,
    "name": "kacie",
    "managerId": 3
  },
  {
    "id": 11,
    "name": "kacie",
    "managerId": 8
  },
  {
    "id": 12,
    "name": "kacie",
    "managerId": 8
  },
  {
    "id": 13,
    "name": "kacie",
    "managerId": 11
  },
  {
    "id": 14,
    "name": "kacie",
    "managerId": 11
  },  
  {
    "id": 15,
    "name": "kacie",
    "managerId": 13
  },  
  {
    "id": 16,
    "name": "kacie",
    "managerId": 13
  }
]
